process_bigraph/__init__.py
process_bigraph/composite.py
process_bigraph/emitter.py
process_bigraph/run.py
process_bigraph/units.py
process_bigraph/experiments/__init__.py
process_bigraph/experiments/minimal_gillespie.py
process_bigraph/processes/__init__.py
process_bigraph/processes/examples.py
process_bigraph/processes/growth_division.py
process_bigraph/processes/parameter_scan.py
process_bigraph/protocols/__init__.py
process_bigraph/protocols/parallel.py
process_bigraph/protocols/rest.py
process_bigraph/protocols/socket.py
process_bigraph/types/__init__.py
process_bigraph/types/process.py
process_bigraph-1.0.5.dist-info/licenses/AUTHORS.md
process_bigraph-1.0.5.dist-info/licenses/LICENSE
process_bigraph-1.0.5.dist-info/METADATA
process_bigraph-1.0.5.dist-info/WHEEL
process_bigraph-1.0.5.dist-info/top_level.txt
process_bigraph-1.0.5.dist-info/RECORD
