Metadata-Version: 2.4
Name: process-bigraph
Version: 1.0.5
Summary: protocol and execution for compositional systems biology
Requires-Python: >=3.11
License-File: LICENSE
License-File: AUTHORS.md
Requires-Dist: bigraph-schema
Requires-Dist: ipdb>=0.13.13
Requires-Dist: matplotlib
Requires-Dist: pint>=0.24.4
Dynamic: license-file
